myopenai/__init__.py
myopenai/myopenai.py
myopenai/pricedata.json
myopenai/test_google_multi_turn.py
myopenai-2.3.6.dist-info/METADATA
myopenai-2.3.6.dist-info/WHEEL
myopenai-2.3.6.dist-info/top_level.txt
myopenai-2.3.6.dist-info/RECORD
