Metadata-Version: 2.2
Name: myopenai
Version: 2.3.6
Summary: A simple OpenAI function package
Home-page: https://github.com/lupin-oomura/myopenai.git
Author: Shin Oomura
Author-email: shin.oomura@gmail.com
Requires-Dist: openai
Requires-Dist: anthropic
Requires-Dist: google-generativeai
Requires-Dist: google-genai
Requires-Dist: python-dotenv
Requires-Dist: requests
Requires-Dist: jsonschema
Requires-Dist: pydantic
Requires-Dist: pyaudio
Dynamic: author
Dynamic: author-email
Dynamic: home-page
Dynamic: requires-dist
Dynamic: summary
